financial_metrics1/__init__.py
financial_metrics1/metrics.py
financial_metrics12-0.999.dist-info/METADATA
financial_metrics12-0.999.dist-info/WHEEL
financial_metrics12-0.999.dist-info/entry_points.txt
financial_metrics12-0.999.dist-info/top_level.txt
financial_metrics12-0.999.dist-info/RECORD
