Metadata-Version: 2.1
Name: financial_metrics12
Version: 0.999
Summary: Package for calculating net profit and ROI.
Home-page: 
Author: Nikita1207
Author-email: dorogin345@gmail.com
Classifier: Development Status :: 3 - Alpha
Classifier: License :: OSI Approved :: MIT License
Classifier: Programming Language :: Python :: 3
Classifier: Topic :: Software Development :: Libraries :: Python Modules
